spacy_glossbert/__init__.py
spacy_glossbert/glossbert_component.py
spacy_glossbert/py.typed
spacy_glossbert/utils.py
spacy_glossbert-0.1.0.dist-info/licenses/LICENSE
spacy_glossbert-0.1.0.dist-info/METADATA
spacy_glossbert-0.1.0.dist-info/WHEEL
spacy_glossbert-0.1.0.dist-info/top_level.txt
spacy_glossbert-0.1.0.dist-info/RECORD
