Metadata-Version: 2.4
Name: spacy-glossbert
Version: 0.1.0
Summary: A spaCy pipeline component for word sense disambiguation using the GlossBERT model
Author-email: Igor Morgado <morgado.igor@gmail.com>
License-Expression: GPL-2.0-only
Classifier: Programming Language :: Python :: 3
Classifier: Operating System :: OS Independent
Classifier: Topic :: Scientific/Engineering :: Artificial Intelligence
Classifier: Topic :: Text Processing :: Linguistic
Requires-Python: >=3.8
License-File: LICENSE
Requires-Dist: spacy>=3.0.0
Requires-Dist: transformers>=4.0.0
Requires-Dist: torch>=1.7.0
Requires-Dist: nltk>=3.6.0
Provides-Extra: dev
Requires-Dist: pytest>=6.0; extra == "dev"
Requires-Dist: isort>=5.0; extra == "dev"
Requires-Dist: mypy>=0.900; extra == "dev"
Requires-Dist: ruff>=0.0.1; extra == "dev"
Dynamic: license-file
